Metadata-Version: 2.1
Name: borsh-python
Version: 0.1.1
Summary: A Borsh library for Python 3.
Home-page: https://github.com/whdev1/borsh-python
Author: whdev1
Author-email: 
License: MIT
Download-URL: https://github.com/whdev1/libborsh-py/archive/refs/tags/v0.1.1.tar.gz
Keywords: Borsh,Binary,Stream
Platform: UNKNOWN
Classifier: Development Status :: 3 - Alpha
Classifier: Intended Audience :: Developers
Classifier: Topic :: Software Development :: Build Tools
Classifier: License :: OSI Approved :: MIT License
Classifier: Programming Language :: Python :: 3
Classifier: Programming Language :: Python :: 3.4
Classifier: Programming Language :: Python :: 3.5
Classifier: Programming Language :: Python :: 3.6
Classifier: Programming Language :: Python :: 3.7
Classifier: Programming Language :: Python :: 3.8
Classifier: Programming Language :: Python :: 3.9
